notebook_httpdbg/__init__.py
notebook_httpdbg/main.py
notebook_httpdbg-0.3.2.dist-info/LICENSE
notebook_httpdbg-0.3.2.dist-info/METADATA
notebook_httpdbg-0.3.2.dist-info/WHEEL
notebook_httpdbg-0.3.2.dist-info/top_level.txt
notebook_httpdbg-0.3.2.dist-info/RECORD
