Metadata-Version: 2.2
Name: notebook-httpdbg
Version: 0.3.2
Summary: A notebook extension to trace HTTP(S) requests.
Author-email: cle-b <cle@tictac.pm>
License: Apache-2.0
Project-URL: Source, https://github.com/cle-b/notebook-httpdbg/
Project-URL: Documentation, https://httpdbg.readthedocs.io/
Classifier: Development Status :: 4 - Beta
Classifier: Intended Audience :: Developers
Classifier: License :: OSI Approved :: Apache Software License
Classifier: Operating System :: OS Independent
Classifier: Programming Language :: Python :: 3
Classifier: Framework :: Jupyter
Classifier: Framework :: IPython
Requires-Python: >=3.9.0
License-File: LICENSE
Requires-Dist: httpdbg>=0.28.1
Requires-Dist: notebook
